pycollo/__init__.py
pycollo/backend.py
pycollo/bounds.py
pycollo/compiled.py
pycollo/expression_graph.py
pycollo/guess.py
pycollo/iteration.py
pycollo/mesh.py
pycollo/mesh_refinement.py
pycollo/nlp.py
pycollo/node.py
pycollo/numbafy.py
pycollo/numbafy_hessian.py
pycollo/operations.py
pycollo/optimal_control_problem.py
pycollo/phase.py
pycollo/quadrature.py
pycollo/scaling.py
pycollo/settings.py
pycollo/sparse.py
pycollo/sparsity.py
pycollo/typing.py
pycollo/utils.py
pycollo/version.py
pycollo/backend/backend.py
pycollo/backend/base.py
pycollo/backend/casadi.py
pycollo/backend/pycollo.py
pycollo/backend/sympy.py
pycollo/solution/__init__.py
pycollo/solution/casadi_solution.py
pycollo/solution/hsad_solution.py
pycollo/solution/pycollo_solution.py
pycollo/solution/solution_abc.py
pycollo/solution/sympy_solution.py
pycollo/vis/__init__.py
pycollo/vis/plot.py
pycollo-0.1.6.dist-info/METADATA
pycollo-0.1.6.dist-info/WHEEL
pycollo-0.1.6.dist-info/top_level.txt
pycollo-0.1.6.dist-info/RECORD
