Metadata-Version: 2.1
Name: pycollo
Version: 0.1.6
Summary: General-purpose optimal control, trajectory optimisation and parameter optimisation using direct collocation
Home-page: https://pycollo.readthedocs.io
Author: Sam Brockie
Author-email: sambrockie@icloud.com
License: MIT
Project-URL: Documentation, https://pycollo.readthedocs.io
Project-URL: PyPI, https://pypi.org/project/pycollo/
Project-URL: conda-forge, https://anaconda.org/conda-forge/pycollo
Project-URL: Source Code, https://github.com/brocksam/pycollo
Project-URL: Bug Tracker, https://github.com/brocksam/pycollo/issues
Classifier: Development Status :: 2 - Pre-Alpha
Classifier: Intended Audience :: Science/Research
Classifier: Programming Language :: Python :: 3
Classifier: Programming Language :: Python :: 3.7
Classifier: Programming Language :: Python :: 3.8
Classifier: Programming Language :: Python :: 3.9
Classifier: License :: OSI Approved :: MIT License
Classifier: Operating System :: OS Independent
Classifier: Natural Language :: English
Classifier: Topic :: Utilities
Requires-Python: >=3.7
Requires-Dist: casadi (>=3.5.5)
Requires-Dist: matplotlib (>=3.3.2)
Requires-Dist: numba (>=0.51.2)
Requires-Dist: numpy (>=1.19.1)
Requires-Dist: pyproprop (>=0.4.10)
Requires-Dist: scipy (>=1.5.2)
Requires-Dist: sympy (>=1.6.2)
Provides-Extra: docs
Requires-Dist: sphinx (>=3.2) ; extra == 'docs'
Requires-Dist: sphinx-autodoc-typehints (>=1.11) ; extra == 'docs'
Requires-Dist: sphinx-rtd-theme (>=0.5) ; extra == 'docs'
Provides-Extra: tests
Requires-Dist: hypothesis (>=5.28) ; extra == 'tests'
Requires-Dist: pytest (>=6.0) ; extra == 'tests'
Requires-Dist: pytest-cases (>=2.2.5) ; extra == 'tests'
Requires-Dist: pytest-cov (>=2.10) ; extra == 'tests'
